aio/core/__init__.py
aio/core/py.typed
aio/core/dev/__init__.py
aio/core/dev/debug.py
aio/core/dev/perf.py
aio/core/directory/__init__.py
aio/core/directory/context.py
aio/core/directory/directory.py
aio/core/directory/utils.py
aio/core/directory/abstract/__init__.py
aio/core/directory/abstract/directory.py
aio/core/event/__init__.py
aio/core/event/executive.py
aio/core/event/loader.py
aio/core/event/reactive.py
aio/core/functional/__init__.py
aio/core/functional/collections.py
aio/core/functional/decorators.py
aio/core/functional/exceptions.py
aio/core/functional/generator.py
aio/core/functional/process.py
aio/core/functional/utils.py
aio/core/log/__init__.py
aio/core/log/logging.py
aio/core/pipe/__init__.py
aio/core/pipe/interface.py
aio/core/pipe/pipe.py
aio/core/pipe/abstract/__init__.py
aio/core/pipe/abstract/pipe.py
aio/core/subprocess/__init__.py
aio/core/subprocess/async_subprocess.py
aio/core/subprocess/exceptions.py
aio/core/subprocess/handler.py
aio/core/tasks/__init__.py
aio/core/tasks/exceptions.py
aio/core/tasks/tasks.py
aio/core/utils/__init__.py
aio/core/utils/context.py
aio/core/utils/data.py
aio/core/utils/date.py
aio/core/utils/exceptions.py
aio/core/utils/resolve.py
aio.core-0.10.5.dist-info/METADATA
aio.core-0.10.5.dist-info/WHEEL
aio.core-0.10.5.dist-info/namespace_packages.txt
aio.core-0.10.5.dist-info/top_level.txt
aio.core-0.10.5.dist-info/RECORD
