Metadata-Version: 2.1
Name: aio.core
Version: 0.10.5
Summary: A collection of functional utils for asyncio
Home-page: https://github.com/envoyproxy/toolshed/tree/main/aio.core
Author: Ryan Northey
Author-email: ryan@synca.io
Maintainer: Ryan Northey
Maintainer-email: ryan@synca.io
License: Apache Software License 2.0
Requires-Python: >=3.10.0
Requires-Dist: abstracts (>=0.0.12)
Requires-Dist: pytz
Requires-Dist: pyyaml
Requires-Dist: trycast (>=0.7.3)
Requires-Dist: types-orjson
Requires-Dist: types-pytz
Requires-Dist: types-pyyaml
